{"SELF-NORMAL-ANY":{"equip":"SELF-NORMAL-ANY","adv":"Gala_Prince","ele":"light","wt":"sword","drg":"Gala_Chronos_Nyx","wep":"sword-light-agito","wps":["An_Ancient_Oath","Emissaries_of_the_Heavens","The_Bridal_Dragon","Dueling_Dancers","Such_High_Spirits","Applelicious_Dreams","Testament_of_Eternity"],"coabs":["Blade","Halloween_Laxi","Peony"],"share":["Weapon","Akasha"],"cond":"85 paralysis res & always connect hits & hit15 & draconic charge","comment":"","real":180.01,"dps":133534,"team":0.10971802467658079,"slices":[["x",3895],["fs",801],["s1",1744],["s2",6850],["s2_paralysis",53],["s3_phase2",1613],["echo",3039],["dx",23003],["ds1",8171],["dfs3",84361]],"stats":{"paralysis":"3.1%","doublebuff":"every 60.00s","echo":"10174.02 avg overdamage att"}},"SELF-NORMAL-MONO":{"equip":"SELF-NORMAL-ANY","adv":"Gala_Prince","ele":"light","wt":"sword","drg":"Gala_Chronos_Nyx","wep":"sword-light-agito","wps":["An_Ancient_Oath","Emissaries_of_the_Heavens","The_Bridal_Dragon","Dueling_Dancers","Such_High_Spirits","Applelicious_Dreams","Testament_of_Eternity"],"coabs":["Blade","Halloween_Laxi","Peony"],"share":["Weapon","Akasha"],"cond":"85 paralysis res & always connect hits & hit15 & draconic charge","comment":"","real":180.01,"dps":133534,"team":0.10971802467658079,"slices":[["x",3895],["fs",801],["s1",1744],["s2",6850],["s2_paralysis",53],["s3_phase2",1613],["echo",3039],["dx",23003],["ds1",8171],["dfs3",84361]],"stats":{"paralysis":"3.1%","doublebuff":"every 60.00s","echo":"10174.02 avg overdamage att"}},"ALWAYS-NORMAL-ANY":{"equip":"ALWAYS-NORMAL-ANY","adv":"Gala_Prince","ele":"light","wt":"sword","drg":"Gala_Chronos_Nyx","wep":"sword-light-agito","wps":["An_Ancient_Oath","Extreme_Teamwork","Spirit_of_the_Season","Dueling_Dancers","Entwined_Flames","A_Kings_Pride_Sword","Savage_Hawk_Lance"],"coabs":["Blade","Halloween_Laxi","Peony"],"share":["Weapon","Akasha"],"cond":"85 paralysis res & always connect hits & hit15 & draconic charge","comment":"","real":180.24,"dps":154009,"team":0.12622089249336252,"slices":[["x",6966],["fs",1433],["s1",1704],["s2",7666],["s2_paralysis",54],["s3_phase2",2199],["echo",2867],["dx",27053],["ds1",7767],["dfs3",96297]],"stats":{"paralysis":"100.0%","flashburn":"100.0%","doublebuff":"every 60.08s","team_att_amp":"1 time from 150.77s","echo":"9609.69 avg overdamage att"}},"ALWAYS-NORMAL-MONO":{"equip":"ALWAYS-NORMAL-ANY","adv":"Gala_Prince","ele":"light","wt":"sword","drg":"Gala_Chronos_Nyx","wep":"sword-light-agito","wps":["An_Ancient_Oath","Extreme_Teamwork","Spirit_of_the_Season","Dueling_Dancers","Entwined_Flames","A_Kings_Pride_Sword","Savage_Hawk_Lance"],"coabs":["Blade","Halloween_Laxi","Peony"],"share":["Weapon","Akasha"],"cond":"85 paralysis res & always connect hits & hit15 & draconic charge","comment":"","real":180.24,"dps":154009,"team":0.12622089249336252,"slices":[["x",6966],["fs",1433],["s1",1704],["s2",7666],["s2_paralysis",54],["s3_phase2",2199],["echo",2867],["dx",27053],["ds1",7767],["dfs3",96297]],"stats":{"paralysis":"100.0%","flashburn":"100.0%","doublebuff":"every 60.08s","team_att_amp":"1 time from 150.77s","echo":"9609.69 avg overdamage att"}},"IMMUNE-NORMAL-ANY":{"equip":"IMMUNE-NORMAL-ANY","adv":"Gala_Prince","ele":"light","wt":"sword","drg":"Gala_Chronos_Nyx","wep":"sword-light-agito","wps":["An_Ancient_Oath","Emissaries_of_the_Heavens","The_Bridal_Dragon","Dueling_Dancers","Such_High_Spirits","Applelicious_Dreams","Testament_of_Eternity"],"coabs":["Cleo","Dagger","Peony"],"share":["Weapon","Akasha"],"cond":"999 all affliction res & hit15 & draconic charge","comment":"","real":180.01,"dps":125629,"team":0.10971802467658079,"slices":[["x",3616],["fs",746],["s1",1604],["s2",6287],["s2_paralysis",0],["s3_phase2",1476],["echo",2897],["dx",21724],["ds1",7576],["dfs3",79699]],"stats":{"doublebuff":"every 60.00s","echo":"9700.28 avg overdamage att"}},"IMMUNE-NORMAL-MONO":{"equip":"IMMUNE-NORMAL-MONO","adv":"Gala_Prince","ele":"light","wt":"sword","drg":"Gala_Chronos_Nyx","wep":"sword-light-agito","wps":["An_Ancient_Oath","Emissaries_of_the_Heavens","The_Bridal_Dragon","Dueling_Dancers","Such_High_Spirits","Applelicious_Dreams","Testament_of_Eternity"],"coabs":["Blade","Halloween_Laxi","Peony"],"share":["Weapon","Summer_Verica"],"cond":"999 all affliction res & always connect hits & hit15 & draconic charge","comment":"","real":180.1,"dps":38793,"team":0.3316946352065618,"slices":[["x",11196],["fs",1957],["s1",12200],["s2",9560],["s2_paralysis",0],["echo",3879]],"stats":{"doublebuff":"every 36.02s","team_att_amp":"1 time from 97.17s","echo":"8623.10 avg overdamage att"}},"SELF-NIHILISM-ANY":{"equip":"SELF-NIHILISM-ANY","adv":"Gala_Prince","ele":"light","wt":"sword","drg":"Gala_Chronos_Nyx","wep":"sword-light-agito","wps":["Adventure_in_the_Past","Pecorines_Grand_Adventure","The_Bridal_Dragon","Dueling_Dancers","Such_High_Spirits","Applelicious_Dreams","Mask_of_Determination_Bow"],"coabs":["Blade","Mitsuhide","Peony"],"share":["Weapon","Humanoid_Mercury"],"cond":"Curse of Nihility & 30 paralysis res & 100 frostbite res & hit15 & hp70 & draconic charge","comment":"","real":180.07,"dps":87064,"team":0.0,"slices":[["x",1696],["fs",413],["s1",1477],["s2",2497],["s2_paralysis",93],["s3_phase2",576],["s4_teamamp",690],["s4_teamamp_frostbite",0],["dx",217],["ds1",4237],["dfs3",75163]],"stats":{"paralysis":"9.9%"}},"SELF-NIHILISM-MONO":{"equip":"SELF-NIHILISM-ANY","adv":"Gala_Prince","ele":"light","wt":"sword","drg":"Gala_Chronos_Nyx","wep":"sword-light-agito","wps":["Adventure_in_the_Past","Pecorines_Grand_Adventure","The_Bridal_Dragon","Dueling_Dancers","Such_High_Spirits","Applelicious_Dreams","Mask_of_Determination_Bow"],"coabs":["Blade","Mitsuhide","Peony"],"share":["Weapon","Humanoid_Mercury"],"cond":"Curse of Nihility & 30 paralysis res & 100 frostbite res & hit15 & hp70 & draconic charge","comment":"","real":180.07,"dps":87064,"team":0.0,"slices":[["x",1696],["fs",413],["s1",1477],["s2",2497],["s2_paralysis",93],["s3_phase2",576],["s4_teamamp",690],["s4_teamamp_frostbite",0],["dx",217],["ds1",4237],["dfs3",75163]],"stats":{"paralysis":"9.9%"}},"ALWAYS-NIHILISM-ANY":{"equip":"ALWAYS-NIHILISM-ANY","adv":"Gala_Prince","ele":"light","wt":"sword","drg":"Gala_Chronos_Nyx","wep":"sword-light-agito","wps":["Extreme_Teamwork","Pecorines_Grand_Adventure","Spirit_of_the_Season","Dueling_Dancers","Entwined_Flames","A_Kings_Pride_Sword","Savage_Hawk_Lance"],"coabs":["Blade","Mitsuhide","Peony"],"share":["Weapon","Akasha"],"cond":"Curse of Nihility & 30 paralysis res & hp70 & hit15 & draconic charge","comment":"","real":180.07,"dps":115824,"team":0.0,"slices":[["x",4039],["fs",389],["s2",3319],["s2_paralysis",109],["s3_phase2",1010],["dx",9622],["ds1",2551],["dfs3",94783]],"stats":{"paralysis":"100.0%","flashburn":"100.0%"}},"ALWAYS-NIHILISM-MONO":{"equip":"ALWAYS-NIHILISM-ANY","adv":"Gala_Prince","ele":"light","wt":"sword","drg":"Gala_Chronos_Nyx","wep":"sword-light-agito","wps":["Extreme_Teamwork","Pecorines_Grand_Adventure","Spirit_of_the_Season","Dueling_Dancers","Entwined_Flames","A_Kings_Pride_Sword","Savage_Hawk_Lance"],"coabs":["Blade","Mitsuhide","Peony"],"share":["Weapon","Akasha"],"cond":"Curse of Nihility & 30 paralysis res & hp70 & hit15 & draconic charge","comment":"","real":180.07,"dps":115824,"team":0.0,"slices":[["x",4039],["fs",389],["s2",3319],["s2_paralysis",109],["s3_phase2",1010],["dx",9622],["ds1",2551],["dfs3",94783]],"stats":{"paralysis":"100.0%","flashburn":"100.0%"}},"IMMUNE-NIHILISM-ANY":{"equip":"IMMUNE-NIHILISM-ANY","adv":"Gala_Prince","ele":"light","wt":"sword","drg":"Gala_Chronos_Nyx","wep":"sword-light-agito","wps":["Adventure_in_the_Past","Pecorines_Grand_Adventure","The_Bridal_Dragon","Dueling_Dancers","Such_High_Spirits","Applelicious_Dreams","Mask_of_Determination_Bow"],"coabs":["Blade","Dagger","Peony"],"share":["Weapon","Humanoid_Mercury"],"cond":"Curse of Nihility & 999 all affliction res & hp70 & draconic charge","comment":"","real":180.07,"dps":86514,"team":0.0,"slices":[["x",1695],["fs",413],["s1",1477],["s2",2496],["s2_paralysis",0],["s3_phase2",576],["s4_teamamp",690],["s4_teamamp_frostbite",0],["dx",217],["ds1",4212],["dfs3",74734]]},"IMMUNE-NIHILISM-MONO":{"equip":"IMMUNE-NIHILISM-ANY","adv":"Gala_Prince","ele":"light","wt":"sword","drg":"Gala_Chronos_Nyx","wep":"sword-light-agito","wps":["Adventure_in_the_Past","Pecorines_Grand_Adventure","The_Bridal_Dragon","Dueling_Dancers","Such_High_Spirits","Applelicious_Dreams","Mask_of_Determination_Bow"],"coabs":["Blade","Dagger","Peony"],"share":["Weapon","Humanoid_Mercury"],"cond":"Curse of Nihility & 999 all affliction res & hp70 & draconic charge","comment":"","real":180.07,"dps":86514,"team":0.0,"slices":[["x",1695],["fs",413],["s1",1477],["s2",2496],["s2_paralysis",0],["s3_phase2",576],["s4_teamamp",690],["s4_teamamp_frostbite",0],["dx",217],["ds1",4212],["dfs3",74734]]}}