{"SELF-NORMAL-ANY":{"equip":"SELF-NORMAL-ANY","adv":"Grace","ele":"shadow","wt":"staff","drg":"Ramiel","wep":"staff-shadow-agito","wps":["An_Ancient_Oath","Emissaries_of_the_Heavens","The_Synthetic_Dragon","Dueling_Dancers","The_Plaguebringer","An_Unfreezing_Flower_Deer","Testament_of_Eternity"],"coabs":["Audric","Forte","Ieyasu"],"share":["Weapon","Gala_Mym"],"cond":"0 poison res & hit15","comment":"","real":180.42,"dps":40445,"team":0.08314018518175852,"slices":[["x",8990],["fs",301],["s4",3247],["dx",22076],["ds1_poison",499],["ds1",5328]],"stats":{"poison":"33.3%","doublebuff":"every 180.42s"}},"SELF-NORMAL-MONO":{"equip":"SELF-NORMAL-ANY","adv":"Grace","ele":"shadow","wt":"staff","drg":"Ramiel","wep":"staff-shadow-agito","wps":["An_Ancient_Oath","Emissaries_of_the_Heavens","The_Synthetic_Dragon","Dueling_Dancers","The_Plaguebringer","An_Unfreezing_Flower_Deer","Testament_of_Eternity"],"coabs":["Audric","Forte","Ieyasu"],"share":["Weapon","Gala_Mym"],"cond":"0 poison res & hit15","comment":"","real":180.42,"dps":40445,"team":0.08314018518175852,"slices":[["x",8990],["fs",301],["s4",3247],["dx",22076],["ds1_poison",499],["ds1",5328]],"stats":{"poison":"33.3%","doublebuff":"every 180.42s"}},"ALWAYS-NORMAL-ANY":{"equip":"ALWAYS-NORMAL-ANY","adv":"Grace","ele":"shadow","wt":"staff","drg":"Gala_Bahamut","wep":"staff-shadow-agito","wps":["Memory_of_a_Friend","Springtime_Breeze","The_Synthetic_Dragon","The_Plaguebringer","The_Queen_of_the_Knife","Testament_of_Eternity","Thunderswift_Lords_Blade_Lance"],"coabs":["Forte","Ieyasu","Summer_Prince"],"share":["Weapon","Humanoid_Mercury"],"cond":"0 frostbite res & hit15","comment":"","real":180.07,"dps":60869,"team":0.033320242607420406,"slices":[["x",11915],["fs",736],["s4_teamamp",7510],["s4_teamamp_frostbite",1170],["dx",28884],["ds1_overcharge2",10652]],"stats":{"poison":"100.0%","frostbite":"69.5%","shadowblight":"100.0%","doublebuff":"every 180.07s","team_att_amp":"every 103.75s from 57.14s","team_defense_amp":"every 103.75s from 57.14s"}},"ALWAYS-NORMAL-MONO":{"equip":"ALWAYS-NORMAL-ANY","adv":"Grace","ele":"shadow","wt":"staff","drg":"Gala_Bahamut","wep":"staff-shadow-agito","wps":["Memory_of_a_Friend","Springtime_Breeze","The_Synthetic_Dragon","The_Plaguebringer","The_Queen_of_the_Knife","Testament_of_Eternity","Thunderswift_Lords_Blade_Lance"],"coabs":["Forte","Ieyasu","Summer_Prince"],"share":["Weapon","Humanoid_Mercury"],"cond":"0 frostbite res & hit15","comment":"","real":180.07,"dps":60869,"team":0.033320242607420406,"slices":[["x",11915],["fs",736],["s4_teamamp",7510],["s4_teamamp_frostbite",1170],["dx",28884],["ds1_overcharge2",10652]],"stats":{"poison":"100.0%","frostbite":"69.5%","shadowblight":"100.0%","doublebuff":"every 180.07s","team_att_amp":"every 103.75s from 57.14s","team_defense_amp":"every 103.75s from 57.14s"}},"IMMUNE-NORMAL-ANY":{"equip":"IMMUNE-NORMAL-ANY","adv":"Grace","ele":"shadow","wt":"staff","drg":"Ramiel","wep":"staff-shadow-agito","wps":["An_Ancient_Oath","Emissaries_of_the_Heavens","The_Synthetic_Dragon","Blessed_Days","Dueling_Dancers"],"coabs":["Audric","Blade","Ieyasu"],"share":["Weapon","Gala_Mym"],"cond":"999 all affliction res & hit15","comment":"","real":180.42,"dps":27341,"team":0.09478075712207565,"slices":[["x",7373],["fs",293],["s4",1733],["dx",15210],["ds1",2730]],"stats":{"doublebuff":"every 180.42s"}},"IMMUNE-NORMAL-MONO":{"equip":"IMMUNE-NORMAL-ANY","adv":"Grace","ele":"shadow","wt":"staff","drg":"Ramiel","wep":"staff-shadow-agito","wps":["An_Ancient_Oath","Emissaries_of_the_Heavens","The_Synthetic_Dragon","Blessed_Days","Dueling_Dancers"],"coabs":["Audric","Blade","Ieyasu"],"share":["Weapon","Gala_Mym"],"cond":"999 all affliction res & hit15","comment":"","real":180.42,"dps":27341,"team":0.09478075712207565,"slices":[["x",7373],["fs",293],["s4",1733],["dx",15210],["ds1",2730]],"stats":{"doublebuff":"every 180.42s"}},"SELF-NIHILISM-ANY":{"equip":"SELF-NIHILISM-ANY","adv":"Grace","ele":"shadow","wt":"staff","drg":"Arsene","wep":"staff-shadow-agito","wps":["Memory_of_a_Friend","Seaside_Princess","The_Lurker_in_the_Woods","A_Small_Courage","The_Queen_of_the_Knife","Testament_of_Eternity","Thunderswift_Lords_Blade_Axe"],"coabs":["Delphi","Ieyasu","Wand"],"share":["Summer_Celliera","Summer_Julietta"],"cond":"Curse of Nihility & 100 bog res & hit15","comment":"","real":180.03,"dps":18667,"team":0.0,"slices":[["x",3389],["s3",4305],["s4",5611],["dx",2698],["ds1",2662]]},"SELF-NIHILISM-MONO":{"equip":"SELF-NIHILISM-ANY","adv":"Grace","ele":"shadow","wt":"staff","drg":"Arsene","wep":"staff-shadow-agito","wps":["Memory_of_a_Friend","Seaside_Princess","The_Lurker_in_the_Woods","A_Small_Courage","The_Queen_of_the_Knife","Testament_of_Eternity","Thunderswift_Lords_Blade_Axe"],"coabs":["Delphi","Ieyasu","Wand"],"share":["Summer_Celliera","Summer_Julietta"],"cond":"Curse of Nihility & 100 bog res & hit15","comment":"","real":180.03,"dps":18667,"team":0.0,"slices":[["x",3389],["s3",4305],["s4",5611],["dx",2698],["ds1",2662]]},"ALWAYS-NIHILISM-ANY":{"equip":"ALWAYS-NIHILISM-ANY","adv":"Grace","ele":"shadow","wt":"staff","drg":"Gala_Reborn_Nidhogg","wep":"staff-shadow-agito","wps":["A_Man_Unchanging","The_Lurker_in_the_Woods","Welcome_to_the_Opera","Dueling_Dancers","Entwined_Flames","Savage_Hawk_Lance","Testament_of_Eternity"],"coabs":["Ieyasu","Joker","Summer_Prince"],"share":["Gala_Mym","Humanoid_Mercury"],"cond":"Curse of Nihility & 100 frostbite res & hit15","comment":"","real":181.06,"dps":33284,"team":0.0,"slices":[["x",4858],["fs",3810],["s3",1859],["s4_teamamp",2581],["s4_teamamp_frostbite",0],["dx",11903],["ds1",8271]],"stats":{"poison":"100.0%","shadowblight":"100.0%"}},"ALWAYS-NIHILISM-MONO":{"equip":"ALWAYS-NIHILISM-ANY","adv":"Grace","ele":"shadow","wt":"staff","drg":"Gala_Reborn_Nidhogg","wep":"staff-shadow-agito","wps":["A_Man_Unchanging","The_Lurker_in_the_Woods","Welcome_to_the_Opera","Dueling_Dancers","Entwined_Flames","Savage_Hawk_Lance","Testament_of_Eternity"],"coabs":["Ieyasu","Joker","Summer_Prince"],"share":["Gala_Mym","Humanoid_Mercury"],"cond":"Curse of Nihility & 100 frostbite res & hit15","comment":"","real":181.06,"dps":33284,"team":0.0,"slices":[["x",4858],["fs",3810],["s3",1859],["s4_teamamp",2581],["s4_teamamp_frostbite",0],["dx",11903],["ds1",8271]],"stats":{"poison":"100.0%","shadowblight":"100.0%"}},"IMMUNE-NIHILISM-ANY":{"equip":"IMMUNE-NIHILISM-ANY","adv":"Grace","ele":"shadow","wt":"staff","drg":"Azazel","wep":"staff-shadow-agito","wps":["Jewels_of_the_Sun","Study_Rabbits","Warrior_Maiden","Bellathorna","From_Whence_He_Comes"],"coabs":["Bow","The_Prince","Tobias"],"share":["Weapon","Karl"],"cond":"Curse of Nihility & 999 all affliction res","comment":"","real":180.09,"dps":1875,"team":0.0,"slices":[["x",1875]]}}