{"SELF-NORMAL-ANY":{"equip":"SELF-NORMAL-ANY","adv":"Irfan","ele":"light","wt":"dagger","drg":"Daikokuten","wep":"dagger-light-agito","wps":["An_Ancient_Oath","Extreme_Teamwork","Memory_of_a_Friend","A_Small_Courage","Dueling_Dancers","Mask_of_Determination_Bow","Testament_of_Eternity"],"coabs":["Blade","Bow","Peony"],"share":["Weapon","Ilia"],"cond":"20 flashburn res & hit15","comment":"","real":180.04,"dps":43211,"team":0.0657922449268746,"slices":[["x",5039],["s1",6748],["s2",3986],["s3_phase2",1877],["s4",2791],["s4_flashburn",464],["dx",18759],["ds",3545]],"stats":{"flashburn":"52.8%"}},"SELF-NORMAL-MONO":{"equip":"SELF-NORMAL-ANY","adv":"Irfan","ele":"light","wt":"dagger","drg":"Daikokuten","wep":"dagger-light-agito","wps":["An_Ancient_Oath","Extreme_Teamwork","Memory_of_a_Friend","A_Small_Courage","Dueling_Dancers","Mask_of_Determination_Bow","Testament_of_Eternity"],"coabs":["Blade","Bow","Peony"],"share":["Weapon","Ilia"],"cond":"20 flashburn res & hit15","comment":"","real":180.04,"dps":43211,"team":0.0657922449268746,"slices":[["x",5039],["s1",6748],["s2",3986],["s3_phase2",1877],["s4",2791],["s4_flashburn",464],["dx",18759],["ds",3545]],"stats":{"flashburn":"52.8%"}},"ALWAYS-NORMAL-ANY":{"equip":"ALWAYS-NORMAL-ANY","adv":"Irfan","ele":"light","wt":"dagger","drg":"Daikokuten","wep":"dagger-light-agito","wps":["Extreme_Teamwork","Memory_of_a_Friend","Spirit_of_the_Season","A_Passion_for_Produce","A_Small_Courage","Mask_of_Determination_Bow","Testament_of_Eternity"],"coabs":["Bow","Dagger2","Peony"],"share":["Weapon","Ilia"],"cond":"20 flashburn res & hit15","comment":"","real":180.04,"dps":51002,"team":0.06579224492687456,"slices":[["x",6681],["s1",7330],["s2",4411],["s3_phase2",2110],["s4",2887],["s4_flashburn",579],["dx",23303],["ds",3700]],"stats":{"paralysis":"100.0%","flashburn":"100.0%"}},"ALWAYS-NORMAL-MONO":{"equip":"ALWAYS-NORMAL-MONO","adv":"Irfan","ele":"light","wt":"dagger","drg":"Daikokuten","wep":"dagger-light-agito","wps":["An_Ancient_Oath","Extreme_Teamwork","Memory_of_a_Friend","A_Small_Courage","Dueling_Dancers","Mask_of_Determination_Bow","Testament_of_Eternity"],"coabs":["Blade","Bow","Peony"],"share":["Weapon","Ilia"],"cond":"20 flashburn res & hit15","comment":"","real":180.05,"dps":47068,"team":0.06894295080164793,"slices":[["x",5457],["s1",7277],["s2",4364],["s3_phase2",2073],["s4",2899],["s4_flashburn",580],["dx",20226],["ds",4188]],"stats":{"paralysis":"100.0%","flashburn":"100.0%"}},"IMMUNE-NORMAL-ANY":{"equip":"IMMUNE-NORMAL-ANY","adv":"Irfan","ele":"light","wt":"dagger","drg":"Daikokuten","wep":"dagger-light-agito","wps":["An_Ancient_Oath","Extreme_Teamwork","Memory_of_a_Friend","A_Small_Courage","Dueling_Dancers","Mask_of_Determination_Bow","Testament_of_Eternity"],"coabs":["Blade","Bow","Peony"],"share":["Weapon","Ilia"],"cond":"999 all affliction res & hit15","comment":"","real":180.04,"dps":38257,"team":0.0657922449268746,"slices":[["x",4395],["s1",5822],["s2",3491],["s3_phase2",1659],["s4",2319],["s4_flashburn",0],["dx",17273],["ds",3294]]},"IMMUNE-NORMAL-MONO":{"equip":"IMMUNE-NORMAL-ANY","adv":"Irfan","ele":"light","wt":"dagger","drg":"Daikokuten","wep":"dagger-light-agito","wps":["An_Ancient_Oath","Extreme_Teamwork","Memory_of_a_Friend","A_Small_Courage","Dueling_Dancers","Mask_of_Determination_Bow","Testament_of_Eternity"],"coabs":["Blade","Bow","Peony"],"share":["Weapon","Ilia"],"cond":"999 all affliction res & hit15","comment":"","real":180.04,"dps":38257,"team":0.0657922449268746,"slices":[["x",4395],["s1",5822],["s2",3491],["s3_phase2",1659],["s4",2319],["s4_flashburn",0],["dx",17273],["ds",3294]]},"SELF-NIHILISM-ANY":{"equip":"SELF-NIHILISM-ANY","adv":"Irfan","ele":"light","wt":"dagger","drg":"Daikokuten","wep":"dagger-light-agito","wps":["An_Ancient_Oath","Extreme_Teamwork","Memory_of_a_Friend","A_Small_Courage","Dueling_Dancers","Mask_of_Determination_Bow","Testament_of_Eternity"],"coabs":["Blade","Bow","Peony"],"share":["Weapon","Ilia"],"cond":"Curse of Nihility & 30 flashburn res & hit15","comment":"","real":180.23,"dps":19840,"team":0.04868282555338913,"slices":[["x",4988],["s1",6324],["s2",3753],["s3_phase2",1727],["s4",2666],["s4_flashburn",381]],"stats":{"flashburn":"53.5%"}},"SELF-NIHILISM-MONO":{"equip":"SELF-NIHILISM-ANY","adv":"Irfan","ele":"light","wt":"dagger","drg":"Daikokuten","wep":"dagger-light-agito","wps":["An_Ancient_Oath","Extreme_Teamwork","Memory_of_a_Friend","A_Small_Courage","Dueling_Dancers","Mask_of_Determination_Bow","Testament_of_Eternity"],"coabs":["Blade","Bow","Peony"],"share":["Weapon","Ilia"],"cond":"Curse of Nihility & 30 flashburn res & hit15","comment":"","real":180.23,"dps":19840,"team":0.04868282555338913,"slices":[["x",4988],["s1",6324],["s2",3753],["s3_phase2",1727],["s4",2666],["s4_flashburn",381]],"stats":{"flashburn":"53.5%"}},"ALWAYS-NIHILISM-ANY":{"equip":"ALWAYS-NIHILISM-ANY","adv":"Irfan","ele":"light","wt":"dagger","drg":"Gala_Reborn_Jeanne","wep":"dagger-light-agito","wps":["Extreme_Teamwork","Memory_of_a_Friend","Spirit_of_the_Season","A_Passion_for_Produce","A_Small_Courage","Mask_of_Determination_Bow","Testament_of_Eternity"],"coabs":["Blade","Peony","Wand"],"share":["Gala_Mym","Ilia"],"cond":"Curse of Nihility & 30 flashburn res & hit15","comment":"","real":180.21,"dps":41393,"team":0.04022895748154666,"slices":[["x",7187],["s1",8992],["s2",4963],["s3",2547],["s4",3566],["s4_flashburn",642],["dx",7564],["ds",5928]],"stats":{"paralysis":"100.0%","flashburn":"100.0%"}},"ALWAYS-NIHILISM-MONO":{"equip":"ALWAYS-NIHILISM-ANY","adv":"Irfan","ele":"light","wt":"dagger","drg":"Gala_Reborn_Jeanne","wep":"dagger-light-agito","wps":["Extreme_Teamwork","Memory_of_a_Friend","Spirit_of_the_Season","A_Passion_for_Produce","A_Small_Courage","Mask_of_Determination_Bow","Testament_of_Eternity"],"coabs":["Blade","Peony","Wand"],"share":["Gala_Mym","Ilia"],"cond":"Curse of Nihility & 30 flashburn res & hit15","comment":"","real":180.21,"dps":41393,"team":0.04022895748154666,"slices":[["x",7187],["s1",8992],["s2",4963],["s3",2547],["s4",3566],["s4_flashburn",642],["dx",7564],["ds",5928]],"stats":{"paralysis":"100.0%","flashburn":"100.0%"}},"IMMUNE-NIHILISM-ANY":{"equip":"IMMUNE-NIHILISM-ANY","adv":"Irfan","ele":"light","wt":"dagger","drg":"Gala_Reborn_Jeanne","wep":"dagger-light-agito","wps":["Extreme_Teamwork","Memory_of_a_Friend","Spirit_of_the_Season","A_Passion_for_Produce","A_Small_Courage","Mask_of_Determination_Bow","Testament_of_Eternity"],"coabs":["Blade","Peony","Wand"],"share":["Gala_Mym","Ilia"],"cond":"Curse of Nihility & 999 all affliction res & hit15","comment":"","real":180.09,"dps":23942,"team":0.049947800258281876,"slices":[["x",6084],["s1",7712],["s2",4308],["s3",2391],["s4",3445],["s4_flashburn",0]]},"IMMUNE-NIHILISM-MONO":{"equip":"IMMUNE-NIHILISM-ANY","adv":"Irfan","ele":"light","wt":"dagger","drg":"Gala_Reborn_Jeanne","wep":"dagger-light-agito","wps":["Extreme_Teamwork","Memory_of_a_Friend","Spirit_of_the_Season","A_Passion_for_Produce","A_Small_Courage","Mask_of_Determination_Bow","Testament_of_Eternity"],"coabs":["Blade","Peony","Wand"],"share":["Gala_Mym","Ilia"],"cond":"Curse of Nihility & 999 all affliction res & hit15","comment":"","real":180.09,"dps":23942,"team":0.049947800258281876,"slices":[["x",6084],["s1",7712],["s2",4308],["s3",2391],["s4",3445],["s4_flashburn",0]]}}