{"SELF-NORMAL-ANY":{"equip":"SELF-NORMAL-ANY","adv":"Lily","ele":"water","wt":"wand","drg":"Gala_Reborn_Poseidon","wep":"wand-water-agito","wps":["Candy_Couriers","Memory_of_a_Friend","Welcome_to_the_Opera","His_Clever_Brother","The_Queen_of_the_Knife"],"coabs":["Blade","Renee","Xander"],"share":["Weapon","Gala_Chelle"],"cond":"100 freeze res & 0 frostbite res & 0 shadowblight res & hp100 & hit15","comment":"","real":180.03,"dps":70802,"team":0.0,"slices":[["x",380],["x_cp",11571],["fs",849],["s1",16831],["s1_frostbite",2787],["s2",10739],["s4",6485],["s4_shadowblight",962],["dx",11551],["ds",8641]],"stats":{"frostbite":"87.8%","shadowblight":"66.6%"}},"SELF-NORMAL-MONO":{"equip":"SELF-NORMAL-ANY","adv":"Lily","ele":"water","wt":"wand","drg":"Gala_Reborn_Poseidon","wep":"wand-water-agito","wps":["Candy_Couriers","Memory_of_a_Friend","Welcome_to_the_Opera","His_Clever_Brother","The_Queen_of_the_Knife"],"coabs":["Blade","Renee","Xander"],"share":["Weapon","Gala_Chelle"],"cond":"100 freeze res & 0 frostbite res & 0 shadowblight res & hp100 & hit15","comment":"","real":180.03,"dps":70802,"team":0.0,"slices":[["x",380],["x_cp",11571],["fs",849],["s1",16831],["s1_frostbite",2787],["s2",10739],["s4",6485],["s4_shadowblight",962],["dx",11551],["ds",8641]],"stats":{"frostbite":"87.8%","shadowblight":"66.6%"}},"ALWAYS-NORMAL-ANY":{"equip":"ALWAYS-NORMAL-ANY","adv":"Lily","ele":"water","wt":"wand","drg":"Gala_Reborn_Poseidon","wep":"wand-water-agito","wps":["An_Ancient_Oath","Candy_Couriers","Memory_of_a_Friend","Dueling_Dancers","His_Clever_Brother"],"coabs":["Blade","Hunter_Sarisse","Xander"],"share":["Weapon","Dragonyule_Lily"],"cond":"100 freeze res & 0 frostbite res & hp100 & always connect hits & hit15","comment":"","real":180.83,"dps":75416,"team":0.12244572079792997,"slices":[["x",150],["x_cp",10160],["fs",1199],["s1",22658],["s1_frostbite",3361],["s2",14056],["echo",3351],["dx",11707],["ds",8769]],"stats":{"frostbite":"100.0%"}},"ALWAYS-NORMAL-MONO":{"equip":"ALWAYS-NORMAL-ANY","adv":"Lily","ele":"water","wt":"wand","drg":"Gala_Reborn_Poseidon","wep":"wand-water-agito","wps":["An_Ancient_Oath","Candy_Couriers","Memory_of_a_Friend","Dueling_Dancers","His_Clever_Brother"],"coabs":["Blade","Hunter_Sarisse","Xander"],"share":["Weapon","Dragonyule_Lily"],"cond":"100 freeze res & 0 frostbite res & hp100 & always connect hits & hit15","comment":"","real":180.83,"dps":75416,"team":0.12244572079792997,"slices":[["x",150],["x_cp",10160],["fs",1199],["s1",22658],["s1_frostbite",3361],["s2",14056],["echo",3351],["dx",11707],["ds",8769]],"stats":{"frostbite":"100.0%"}},"IMMUNE-NORMAL-ANY":{"equip":"IMMUNE-NORMAL-ANY","adv":"Lily","ele":"water","wt":"wand","drg":"Gala_Reborn_Poseidon","wep":"wand-water-agito","wps":["Candy_Couriers","Memory_of_a_Friend","Welcome_to_the_Opera","Snipers_Allure","The_Queen_of_the_Knife"],"coabs":["Blade","Renee","Xander"],"share":["Weapon","Gala_Chelle"],"cond":"999 all affliction res & hp100 & hit15","comment":"","real":180.2,"dps":43637,"team":0.0,"slices":[["x",259],["x_cp",6939],["fs",737],["s1",10677],["s1_frostbite",0],["s2",6568],["s4",4638],["s4_shadowblight",0],["dx",8539],["ds",5276]]},"IMMUNE-NORMAL-MONO":{"equip":"IMMUNE-NORMAL-ANY","adv":"Lily","ele":"water","wt":"wand","drg":"Gala_Reborn_Poseidon","wep":"wand-water-agito","wps":["Candy_Couriers","Memory_of_a_Friend","Welcome_to_the_Opera","Snipers_Allure","The_Queen_of_the_Knife"],"coabs":["Blade","Renee","Xander"],"share":["Weapon","Gala_Chelle"],"cond":"999 all affliction res & hp100 & hit15","comment":"","real":180.2,"dps":43637,"team":0.0,"slices":[["x",259],["x_cp",6939],["fs",737],["s1",10677],["s1_frostbite",0],["s2",6568],["s4",4638],["s4_shadowblight",0],["dx",8539],["ds",5276]]},"SELF-NIHILISM-ANY":{"equip":"SELF-NORMAL-ANY","adv":"Lily","ele":"water","wt":"wand","drg":"Gala_Reborn_Poseidon","wep":"wand-water-agito","wps":["Candy_Couriers","Memory_of_a_Friend","Welcome_to_the_Opera","His_Clever_Brother","The_Queen_of_the_Knife"],"coabs":["Blade","Dagger","Xander"],"share":["Weapon","Gala_Chelle"],"cond":"Curse of Nihility & 100 freeze res & 0 frostbite res & 0 shadowblight res & hp100","comment":"","real":180.09,"dps":43745,"team":0.0,"slices":[["x",5618],["fs",359],["s1",10998],["s1_frostbite",1717],["s2",6622],["s4",3597],["s4_shadowblight",591],["dx",8124],["ds",6116]],"stats":{"frostbite":"84.3%","shadowblight":"58.3%"}},"SELF-NIHILISM-MONO":{"equip":"SELF-NORMAL-ANY","adv":"Lily","ele":"water","wt":"wand","drg":"Gala_Reborn_Poseidon","wep":"wand-water-agito","wps":["Candy_Couriers","Memory_of_a_Friend","Welcome_to_the_Opera","His_Clever_Brother","The_Queen_of_the_Knife"],"coabs":["Blade","Dagger","Xander"],"share":["Weapon","Gala_Chelle"],"cond":"Curse of Nihility & 100 freeze res & 0 frostbite res & 0 shadowblight res & hp100","comment":"","real":180.09,"dps":43745,"team":0.0,"slices":[["x",5618],["fs",359],["s1",10998],["s1_frostbite",1717],["s2",6622],["s4",3597],["s4_shadowblight",591],["dx",8124],["ds",6116]],"stats":{"frostbite":"84.3%","shadowblight":"58.3%"}},"ALWAYS-NIHILISM-ANY":{"equip":"SELF-NORMAL-ANY","adv":"Lily","ele":"water","wt":"wand","drg":"Gala_Reborn_Poseidon","wep":"wand-water-agito","wps":["Candy_Couriers","Memory_of_a_Friend","Welcome_to_the_Opera","His_Clever_Brother","The_Queen_of_the_Knife"],"coabs":["Blade","Dagger","Xander"],"share":["Weapon","Gala_Chelle"],"cond":"Curse of Nihility & 100 freeze res & 0 frostbite res & 0 shadowblight res & hp100","comment":"","real":180.09,"dps":43745,"team":0.0,"slices":[["x",5618],["fs",359],["s1",10998],["s1_frostbite",1717],["s2",6622],["s4",3597],["s4_shadowblight",591],["dx",8124],["ds",6116]],"stats":{"frostbite":"84.3%","shadowblight":"58.3%"}},"ALWAYS-NIHILISM-MONO":{"equip":"SELF-NORMAL-ANY","adv":"Lily","ele":"water","wt":"wand","drg":"Gala_Reborn_Poseidon","wep":"wand-water-agito","wps":["Candy_Couriers","Memory_of_a_Friend","Welcome_to_the_Opera","His_Clever_Brother","The_Queen_of_the_Knife"],"coabs":["Blade","Dagger","Xander"],"share":["Weapon","Gala_Chelle"],"cond":"Curse of Nihility & 100 freeze res & 0 frostbite res & 0 shadowblight res & hp100","comment":"","real":180.09,"dps":43745,"team":0.0,"slices":[["x",5618],["fs",359],["s1",10998],["s1_frostbite",1717],["s2",6622],["s4",3597],["s4_shadowblight",591],["dx",8124],["ds",6116]],"stats":{"frostbite":"84.3%","shadowblight":"58.3%"}},"IMMUNE-NIHILISM-ANY":{"equip":"SELF-NORMAL-ANY","adv":"Lily","ele":"water","wt":"wand","drg":"Gala_Reborn_Poseidon","wep":"wand-water-agito","wps":["Candy_Couriers","Memory_of_a_Friend","Welcome_to_the_Opera","His_Clever_Brother","The_Queen_of_the_Knife"],"coabs":["Blade","Dagger","Xander"],"share":["Weapon","Gala_Chelle"],"cond":"Curse of Nihility & 100 freeze res & 0 frostbite res & 0 shadowblight res & hp100","comment":"","real":180.09,"dps":43745,"team":0.0,"slices":[["x",5618],["fs",359],["s1",10998],["s1_frostbite",1717],["s2",6622],["s4",3597],["s4_shadowblight",591],["dx",8124],["ds",6116]],"stats":{"frostbite":"84.3%","shadowblight":"58.3%"}},"IMMUNE-NIHILISM-MONO":{"equip":"SELF-NORMAL-ANY","adv":"Lily","ele":"water","wt":"wand","drg":"Gala_Reborn_Poseidon","wep":"wand-water-agito","wps":["Candy_Couriers","Memory_of_a_Friend","Welcome_to_the_Opera","His_Clever_Brother","The_Queen_of_the_Knife"],"coabs":["Blade","Dagger","Xander"],"share":["Weapon","Gala_Chelle"],"cond":"Curse of Nihility & 100 freeze res & 0 frostbite res & 0 shadowblight res & hp100","comment":"","real":180.09,"dps":43745,"team":0.0,"slices":[["x",5618],["fs",359],["s1",10998],["s1_frostbite",1717],["s2",6622],["s4",3597],["s4_shadowblight",591],["dx",8124],["ds",6116]],"stats":{"frostbite":"84.3%","shadowblight":"58.3%"}}}