{"SELF-NORMAL-ANY":{"equip":"SELF-NORMAL-ANY","adv":"Pinon","ele":"water","wt":"bow","variant":"UNLOCKED","drg":"Gala_Reborn_Poseidon","wep":"bow-water-agito","wps":["Dear_Diary","Memory_of_a_Friend","The_Lurker_in_the_Woods","Chariot_Drift","His_Clever_Brother"],"coabs":["Blade","Dragonyule_Cleo","Grace"],"share":["Weapon","Hunter_Sarisse"],"cond":"0 frostbite res & hp70 & hit15","comment":"unlock at 0.00s","real":180.77,"dps":80244,"team":0.0,"slices":[["fs2",55392],["s1",5242],["s1_frostbite",795],["s4",2165],["dx",11877],["ds",4771]],"stats":{"frostbite":"77.8%"}},"SELF-NORMAL-MONO":{"equip":"SELF-NORMAL-MONO","adv":"Pinon","ele":"water","wt":"bow","variant":"UNLOCKED","drg":"Gala_Reborn_Poseidon","wep":"bow-water-agito","wps":["Dear_Diary","Memory_of_a_Friend","The_Lurker_in_the_Woods","Chariot_Drift","His_Clever_Brother"],"coabs":["Blade","Catherine","Dragonyule_Cleo"],"share":["Weapon","Hunter_Sarisse"],"cond":"0 frostbite res & hp70 & hit15","comment":"unlock at 0.00s","real":180.77,"dps":76281,"team":0.0,"slices":[["fs2",49527],["s1",5645],["s1_frostbite",856],["s4",2331],["dx",12785],["ds",5136]],"stats":{"frostbite":"77.8%"}},"ALWAYS-NORMAL-ANY":{"equip":"ALWAYS-NORMAL-ANY","adv":"Pinon","ele":"water","wt":"bow","variant":"UNLOCKED","drg":"Gala_Reborn_Poseidon","wep":"bow-water-agito","wps":["Dear_Diary","Memory_of_a_Friend","The_Lurker_in_the_Woods","Chariot_Drift","His_Clever_Brother"],"coabs":["Dragonyule_Cleo","Gala_Mascula","Grace"],"share":["Weapon","Hunter_Sarisse"],"cond":"0 frostbite res & hp70 & hit10 & hit15","comment":"unlock at 0.00s","real":180.77,"dps":89354,"team":0.0,"slices":[["fs2",62667],["s1",5706],["s1_frostbite",866],["s4",2182],["dx",12692],["ds",5239]],"stats":{"frostbite":"100.0%"}},"ALWAYS-NORMAL-MONO":{"equip":"ALWAYS-NORMAL-MONO","adv":"Pinon","ele":"water","wt":"bow","variant":"UNLOCKED","drg":"Gala_Reborn_Poseidon","wep":"bow-water-agito","wps":["Dear_Diary","Memory_of_a_Friend","The_Lurker_in_the_Woods","Chariot_Drift","His_Clever_Brother"],"coabs":["Blade","Dragonyule_Cleo","Xander"],"share":["Weapon","Hunter_Sarisse"],"cond":"0 frostbite res & hp70 & hit15","comment":"unlock at 0.00s","real":180.77,"dps":82291,"team":0.0,"slices":[["fs2",54102],["s1",5889],["s1_frostbite",861],["s4",2135],["dx",13663],["ds",5640]],"stats":{"frostbite":"100.0%"}},"IMMUNE-NORMAL-ANY":{"equip":"IMMUNE-NORMAL-ANY","adv":"Pinon","ele":"water","wt":"bow","variant":"UNLOCKED","drg":"Gala_Reborn_Poseidon","wep":"bow-water-agito","wps":["Dear_Diary","Memory_of_a_Friend","The_Lurker_in_the_Woods","Flowers_Under_the_Moon","Snipers_Allure"],"coabs":["Blade","Dragonyule_Cleo","Grace"],"share":["Weapon","Hunter_Sarisse"],"cond":"999 all affliction res & hp70 & hit15","comment":"unlock at 0.00s","real":180.26,"dps":40142,"team":0.0,"slices":[["fs2",17391],["s1",6044],["s1_frostbite",0],["s4",1812],["dx",10541],["ds",4351]]},"IMMUNE-NORMAL-MONO":{"equip":"IMMUNE-NORMAL-MONO","adv":"Pinon","ele":"water","wt":"bow","variant":"UNLOCKED","drg":"Gaibhne_and_Creidhne","wep":"bow-water-agito","wps":["Dear_Diary","Forest_Bonds","Proper_Maintenance","Beach_Battle","His_Clever_Brother"],"coabs":["Blade","Summer_Celliera","Summer_Estelle"],"share":["Templar_Hope","Elisanne"],"cond":"999 all affliction res & hp70","comment":"unlock at 0.00s","real":180.04,"dps":25839,"team":0.24183134118478977,"slices":[["x_sigil",7481],["s1",14428],["s1_frostbite",0],["s4",1199],["dx",2730]],"stats":{"doublebuff":"every 30.01s"}},"SELF-NIHILISM-ANY":{"equip":"SELF-NIHILISM-ANY","adv":"Pinon","ele":"water","wt":"bow","variant":"UNLOCKED","drg":"Gala_Reborn_Poseidon","wep":"bow-water-agito","wps":["Dear_Diary","Memory_of_a_Friend","The_Lurker_in_the_Woods","Flowers_Under_the_Moon","His_Clever_Brother"],"coabs":["Dragonyule_Cleo","Grace","Summer_Ranzal"],"share":["Summer_Celliera","Dragonyule_Lily"],"cond":"Curse of Nihility & 0 frostbite res & 100 bog res & hit15","comment":"unlock at 0.00s","real":181.53,"dps":58438,"team":0.0,"slices":[["fs2",39178],["s1",3377],["s1_frostbite",500],["s3",1892],["echo",1580],["dx",8169],["ds",3740]],"stats":{"frostbite":"77.1%"}},"SELF-NIHILISM-MONO":{"equip":"SELF-NIHILISM-MONO","adv":"Pinon","ele":"water","wt":"bow","variant":"UNLOCKED","drg":"Gala_Reborn_Poseidon","wep":"bow-water-agito","wps":["Forest_Bonds","Memory_of_a_Friend","The_Lurker_in_the_Woods","His_Clever_Brother","The_Queen_of_the_Knife"],"coabs":["Blade","Dragonyule_Cleo","Summer_Estelle"],"share":["Summer_Julietta","Karina"],"cond":"Curse of Nihility & 0 frostbite res & 100 bog res & hit15","comment":"unlock at 0.00s","real":181.27,"dps":56706,"team":0.0,"slices":[["fs2",32669],["s1",7587],["s1_frostbite",966],["s3",3596],["s4",2099],["s4_frostbite",477],["dx",3454],["ds",5854]],"stats":{"frostbite":"83.4%"}},"ALWAYS-NIHILISM-ANY":{"equip":"ALWAYS-NIHILISM-ANY","adv":"Pinon","ele":"water","wt":"bow","variant":"UNLOCKED","drg":"Gala_Reborn_Poseidon","wep":"bow-water-agito","wps":["Forest_Bonds","Memory_of_a_Friend","The_Lurker_in_the_Woods","His_Clever_Brother","The_Queen_of_the_Knife"],"coabs":["Dragonyule_Cleo","Gala_Mascula","Grace"],"share":["Summer_Celliera","Summer_Julietta"],"cond":"Curse of Nihility & 0 frostbite res & 100 bog res & hit10 & hit15","comment":"unlock at 0.00s","real":181.27,"dps":66478,"team":0.0,"slices":[["fs2",42578],["s1",5545],["s1_frostbite",736],["s3",2626],["s4",3143],["dx",6680],["ds",5167]],"stats":{"frostbite":"100.0%"}},"ALWAYS-NIHILISM-MONO":{"equip":"ALWAYS-NIHILISM-MONO","adv":"Pinon","ele":"water","wt":"bow","variant":"UNLOCKED","drg":"Gala_Reborn_Poseidon","wep":"bow-water-agito","wps":["Forest_Bonds","Memory_of_a_Friend","The_Lurker_in_the_Woods","His_Clever_Brother","The_Queen_of_the_Knife"],"coabs":["Dragonyule_Cleo","Gala_Mascula","Yurius"],"share":["Summer_Julietta","Karina"],"cond":"Curse of Nihility & 0 frostbite res & 100 bog res & hit10 & hit15","comment":"unlock at 0.00s","real":180.0,"dps":62410,"team":0.0,"slices":[["fs2",36666],["s1",6970],["s1_frostbite",962],["s3",3640],["s4",2130],["s4_frostbite",484],["dx",5025],["ds",6528]],"stats":{"frostbite":"100.0%"}},"IMMUNE-NIHILISM-ANY":{"equip":"IMMUNE-NIHILISM-ANY","adv":"Pinon","ele":"water","wt":"bow","variant":"UNLOCKED","drg":"Gala_Reborn_Poseidon","wep":"bow-water-agito","wps":["Dear_Diary","Memory_of_a_Friend","The_Lurker_in_the_Woods","Flowers_Under_the_Moon","His_Clever_Brother"],"coabs":["Blade","Dagger","Grace"],"share":["Summer_Celliera","Nevin"],"cond":"Curse of Nihility & 999 all affliction res","comment":"unlock at 0.00s","real":181.87,"dps":25919,"team":0.0,"slices":[["fs2",10720],["s1",3165],["s1_frostbite",0],["s3",1434],["s4",767],["dx",6586],["ds",3244]]}}